Workbook
Name ListaClientes: tblClientes[ID_Cliente]
Name ListaCondiciones: Data_Clientes!$E$4:$E$6
Name RangoHistorico: OFFSET(Historico_Simulaciones!$A$2,0,0,MAX(1,COUNTA(Historico_Simulaciones!$A:$A)-1),7)
Name RutaProyecto: Configuracion!$B$1
Name SegmentaciónDeDatos_Categoria_Agrupador: #N/A
Name SegmentaciónDeDatos_Categoria_Agrupador1: #N/A
Name SegmentaciónDeDatos_Region_Geografica: #N/A
Name SegmentaciónDeDatos_Region_Geografica1: #N/A
Name SegmentaciónDeDatos_Trimestre: #N/A

Sheet Dashboard
A1: SIMULADOR FINANCIERO
A3: Datos del Cliente
A4: ID Cliente | B4: CLI003
A5: Nombre | B5: =IFERROR(_xlfn.XLOOKUP(B4,tblClientes[ID_Cliente],tblClientes[Nombre]),"") -> Lucía Fernández
A6: Empresa | B6: =IFERROR(_xlfn.XLOOKUP(B4,tblClientes[ID_Cliente],tblClientes[Empresa]),"") -> Patagonia Servicios S.A.
A7: Condición de Crédito
A8: ID Condicion | B8: COND03
A9: Condicion | B9: =IFERROR(_xlfn.XLOOKUP(B8,Data_Clientes!$E$4:$E$6,Data_Clientes!$F$4:$F$6),"") -> Largo Plazo
A10: Tasa Anual | B10: =IFERROR(_xlfn.XLOOKUP(B8,Data_Clientes!$E$4:$E$6,Data_Clientes!$G$4:$G$6),"") -> 0.18
A11: Plazo en meses | B11: =IFERROR(_xlfn.XLOOKUP(B8,Data_Clientes!$E$4:$E$6,Data_Clientes!$H$4:$H$6),"") -> 36
A12: Monto a simular | B12: 20000000
A13: Resultados
A14: Cuota Mensual | B14: =IF(OR(B12="",B10="",B11=""),"",PMT(B10/12,B11,-B12)) -> 723047.91
A15: Valor Futuro | B15: =IF(OR(B12="",B10="",B11=""),"",FV(B10/12,B11,0,-B12)) -> 34182791

Sheet Data_Clientes
J2: Modelo Relacional
A3: ID_Cliente | B3: Nombre | C3: Empresa | E3: ID_Condicion | F3: Condicion | G3: Tasa_Anual | H3: Plazo_Meses
A4: CLI001 | B4: Ana Gómez | C4: Andina S.A. | E4: COND01 | F4: Corto Plazo | G4: 0.24 | H4: 12 | J4: tblClientes PK: ID_Cliente | M4: tblCondicionesCredito PK: ID_Condicion
A5: CLI002 | B5: Martín López | C5: Norte Comercial S.R.L. | E5: COND02 | F5: Mediano Plazo | G5: 0.21 | H5: 24
A6: CLI003 | B6: Lucía Fernández | C6: Patagonia Servicios S.A. | E6: COND03 | F6: Largo Plazo | G6: 0.18 | H6: 36
A7: CLI004 | B7: Diego Romero | C7: Centro Logística S.R.L.
A8: CLI005 | B8: Sofía Martínez | C8: Delta Tecnología S.A.

Sheet Historico_Simulaciones
A1: ID_Simulacion | B1: Fecha_Hora | C1: ID_Cliente | D1: ID_Condicion | E1: Monto | F1: Cuota_Mensual | G1: Valor_Futuro | I1: Claves del Histórico
A2: SIM001 | B2: 46262.861 | C2: CLI001 | D2: COND01 | E2: 10000000 | F2: 945595.97 | G2: 12682418
A3: SIM002 | B3: 46262.868 | C3: CLI002 | D3: COND02 | E3: 15000000 | F3: 770784.76 | G3: 22746642 | I3: PK: ID_Simulacion
A4: SIM003 | B4: 46264.977 | C4: CLI002 | D4: COND02 | E4: 15000000 | F4: 770784.76 | G4: 22746642 | I4: FK: ID_Cliente → tblClientes
A5: SIM004 | B5: 46264.98 | C5: CLI003 | D5: COND03 | E5: 20000000 | F5: 723047.91 | G5: 34182791 | I5: FK: ID_Condicion → tblCondicionesCredito

Sheet Evaluación_Financiera
A2: EVALUACIÓN FINANCIERA DEL PROYECTO
A4: FINANCIAMIENTO
A5: Inversión inicial | B5: 8000000
A6: Monto financiado | B6: 5000000
A7: Tasa anual | B7: 0.18
A8: Plazo (meses) | B8: 36
A9: Cuota mensual | B9: =-PMT(B7/12,B8,B6) -> 180761.98
A12: EVALUACIÓN DEL PROYECTO
A13: Costo de capital | B13: 0.15
A15: Año 0 | B15: -8000000
A16: Año 1 | B16: 2000000
A17: Año 2 | B17: 2300000
A18: Año 3 | B18: 2600000
A19: Año 4 | B19: 3000000
A20: Año 5 | B20: 3400000
A22: VAN | B22: =NPV(B13,B16:B20)+B15 -> 593463.71
A23: TIR | B23: =IRR(B15:B20) -> 0.17812413
A24: Conclusion | B24: =IF(AND(B22>0,B23>B13),"PROYECTO VIABLE - El VAN es positivo y la TIR supera el costo de capital.","PROYECTO NO VIABLE - El VAN no es positivo o la TIR no supera el costo de capital.") -> PROYECTO VIABLE - El VAN es positivo y la TIR supera el costo de capital.

Sheet Estadistica_Descriptiva
A1: Facturacion_Neta
A3: Media | B3: 2720582.4
A4: Error típico | B4: 14644.708
A5: Mediana | B5: 2108699.7
A6: Moda | B6: 5067210
A7: Desviación estándar | B7: 2172161.3
A8: Varianza de la muestra | B8: 4.7182845e+12
A9: Curtosis | B9: 0.14051751
A10: Coeficiente de asimetría | B10: 0.95098717
A11: Rango | B11: 10125175
A12: Mínimo | B12: 39725.12
A13: Máximo | B13: 10164900
A14: Suma | B14: 5.9852813e+10
A15: Cuenta | B15: 22000

Sheet Base_Estadistica
A1: Facturacion_Neta
A2: 7711329.6
A3: 1492900
A4: 3744223.4
A5: 3408312
A6: 289599
A7: 619930
A8: 2492856
A9: 660447.32
A10: 934434.72
A11: 2000447.8
A12: 2174907.3
A13: 5153952.2
... A22001: 4249593.4

Sheet Resumen de Escenarios
B2: Resumen del escenario
D3: Valores actuales: | E3: Pesimista | F3: Base (Actual) | G3: Optimista
E4: Creado por Operador el 08/09/2026 | F4: Creado por Operador el 08/09/2026 | G4: Creado por Operador el 08/09/2026
B5: Celdas cambiantes:
C6: $B$4 | D6: 180000 | E6: 165000 | F6: 180000 | G6: 195000
C7: $B$5 | D7: 80 | E7: 60 | F7: 80 | G7: 100
C8: $B$6 | D8: 120000 | E8: 125000 | F8: 120000 | G8: 115000
B9: Celdas de resultado:
C10: $B$11 | D10: 2300000 | E10: -100000 | F10: 2300000 | G10: 5500000
B11: Notas: La columna de valores actuales representa los valores de las celdas cambiantes
B12: en el momento en que se creó el Informe resumen de escenario. Las celdas cambiantes de
B13: cada escenario se muestran en gris.

Sheet Simulacion_Financiera
A2: SIMULACIÓN FINANCIERA
A4: Precio unitario | B4: 180000
A5: Unidades proyectadas | B5: 80
A6: Costo variable unitario | B6: 120000
A7: Costos fijos | B7: 2500000
A9: Ingresos proyectados | B9: =B4*B5 -> 14400000
A10: Costos variables | B10: =B6*B5 -> 9600000
A11: Beneficio neto | B11: =B9-B10-B7 -> 2300000
A13: Meta de beneficio | B13: 500000
A15: RESULTADO BUSCAR OBJETIVO
A16: Meta de beneficio | B16: 500000
A17: Unidades necesarias | B17: 50
A18: Procedimiento | B18: Definir B11 en $500.000 cambiando B5

Sheet Configuracion
A1: Ruta del proyecto | B1: {=LEFT(CELL("nombrearchivo",A1),SEARCH("[",CELL("nombrearchivo",A1))-1)} -> C:\Users\Operador\Desktop\CARLA\DATA ANALYTICS\PRE ENTREGA 9\

Sheet Reporte_Ejecutivo
A1: REPORTE EJECUTIVO DE FACTURACIÓN
A3: Análisis por región y categoría de producto
A4: Fecha | B4: All
A6: Total Ventas | B6: Etiquetas de columna
A7: Etiquetas de fila | B7: Electrónica | C7: Hogar | D7: Línea Blanca | E7: Tecnología | F7: Total general
A8: Buenos Aires | B8: 2.9347851e+09 | C8: 2.9755747e+09 | D8: 2.9222231e+09 | E8: 3.1813618e+09 | F8: 1.2013945e+10
A9: Córdoba | B9: 5.7603353e+09 | C9: 6.1304725e+09 | D9: 5.7460464e+09 | E9: 5.8969088e+09 | F9: 2.3533763e+10
A10: Mendoza | B10: 6.10294e+09 | C10: 5.693942e+09 | D10: 5.9645192e+09 | E10: 6.0137204e+09 | F10: 2.3775122e+10
A11: Sin informar | B11: 1.7384114e+08 | C11: 77974143 | D11: 1.0601993e+08 | E11: 1.7214879e+08 | F11: 5.29984e+08
A12: Total general | B12: 1.4971902e+10 | C12: 1.4877963e+10 | D12: 1.4738809e+10 | E12: 1.526414e+10 | F12: 5.9852813e+10

Sheet Dashboard Final
A1: DASHBOARD EJECUTIVO DE VENTAS
A3: Retail | Análisis de ventas y comportamiento comercial – 2026
A5: VENTAS TOTALES | D5: TICKET PROMEDIO | G5: TRANSACCIONES | J5: UNIDADES VENDIDAS
A6: =Soporte_Dashboard_M9!A2 -> 5.9852813e+10 | D6: =Soporte_Dashboard_M9!B2 -> 2720582.4 | G6: =Soporte_Dashboard_M9!C2 -> 22000 | J6: =Soporte_Dashboard_M9!D2 -> 142550
B26: INSIGHT DINAMICO | I26: INSIGHT POR CATEGORÍA

Sheet Soporte_Dashboard_M9
A1: Total Ventas | B1: Venta Promedio por Transaccion | C1: Cantidad Transacciones | D1: Unidades Vendidas
A2: 5.9852813e+10 | B2: 2720582.4 | C2: 22000 | D2: 142550 | M2: =GETPIVOTDATA("[Measures].[Total Ventas]",$G$6) -> 5.9852813e+10
M3: ="Facturación seleccionada: $ "&TEXT(M2/1000000,"#.##0")&" M" -> Facturación seleccionada: $ 59.853 M
M4: =IFERROR("Dentro de la selección, "&PROPER(INDEX($A$7:$A$18,MATCH(MAX($B$7:$B$18),$B$7:$B$18,0)))&" registra la mayor facturación: $ "&TEXT(MAX($B$7:$B$18)/1000000,"#.##0")&" M","Sin datos para la selección") -> Dentro de la selección, Julio registra la mayor facturación: $ 5.253 M
M5: =IFERROR("La categoría líder es "&INDEX($D$7:$D$10,MATCH(MAX($E$7:$E$10),$E$7:$E$10,0))&", con $ "&TEXT(MAX($E$7:$E$10)/1000000,"#.##0")&" M de facturación.","Sin datos para la selección") -> La categoría líder es Tecnología, con $ 15.264 M de facturación.
A6: Mes | B6: Total Ventas | D6: Categoria | E6: Total Ventas | G6: Trimestre | H6: Total Ventas | J6: Trimestre | K6: Facturación
A7: enero | B7: 5.1288813e+09 | D7: Electrónica | E7: 1.4971902e+10 | G7: 1 | H7: 1.4851589e+10 | J7: T1 | K7: =IFERROR(GETPIVOTDATA("[Measures].[Total Ventas]",$G$6,"[Dim_Calendario].[Trimestre]","[Dim_Calendario].[Trimestre].&[1]"),0) -> 1.4851589e+10
A8: febrero | B8: 4.5309169e+09 | D8: Hogar | E8: 1.4877963e+10 | G8: 2 | H8: 1.4775295e+10 | J8: T2 | K8: =IFERROR(GETPIVOTDATA("[Measures].[Total Ventas]",$G$6,"[Dim_Calendario].[Trimestre]","[Dim_Calendario].[Trimestre].&[2]"),0) -> 1.4775295e+10
A9: marzo | B9: 5.1917904e+09 | D9: Línea Blanca | E9: 1.4738809e+10 | G9: 3 | H9: 1.5084937e+10 | J9: T3 | K9: =IFERROR(GETPIVOTDATA("[Measures].[Total Ventas]",$G$6,"[Dim_Calendario].[Trimestre]","[Dim_Calendario].[Trimestre].&[3]"),0) -> 1.5084937e+10
A10: abril | B10: 4.9974567e+09 | D10: Tecnología | E10: 1.526414e+10 | G10: 4 | H10: 1.5140993e+10 | J10: T4 | K10: =IFERROR(GETPIVOTDATA("[Measures].[Total Ventas]",$G$6,"[Dim_Calendario].[Trimestre]","[Dim_Calendario].[Trimestre].&[4]"),0) -> 1.5140993e+10
A11: mayo | B11: 4.7545103e+09 | G11: Total general | H11: 5.9852813e+10 | J11: Total | K11: =SUM(K7:K10) -> 5.9852813e+10
A12: junio | B12: 5.0233277e+09
A13: julio | B13: 5.2531136e+09
A14: agosto | B14: 5.0148469e+09
A15: septiembre | B15: 4.8169761e+09
A16: octubre | B16: 5.1405358e+09
A17: noviembre | B17: 4.9771757e+09
A18: diciembre | B18: 5.0232819e+09

Sheet Registro_IA_M9
A1: REGISTRO DE ANÁLISIS ASISTIDO POR IA
A2: Etapa | B2: Contenido
A3: Conclusión 1 | B3: Al observar la evolución de la facturación mensual, marzo y julio registran los niveles más altos del período, con aproximadamente $5.191 M y $5.253 M, respectivamente, destacándose como los meses de mayor facturación.
A4: Conclusión 2 | B4: Entre las categorías analizadas, Tecnología concentra la mayor facturación, con aproximadamente $15.264 M, posicionándose como la categoría de mayor peso dentro de las ventas totales.
A5: Conclusión 3 | B5: En la distribución trimestral, el cuarto trimestre presenta el mayor aporte a la facturación total. Sin embargo, las diferencias entre trimestres son relativamente acotadas, por lo que con los datos disponibles no es posible afirmar una tendencia estacional ni determinar con certeza la causa de este comportamiento.
A6: Prompt enviado a ChatGPT | B6: A partir de las siguientes conclusiones obtenidas del análisis de mi dashboard de ventas, realizá una revisión crítica actuando como “abogado del diablo”. Identificá posibles sesgos, interpretaciones apresuradas o variables omitidas. Proponé explicaciones alternativas sin asumir causas que los datos no demuestren. Indicame qué información adicional sería útil analizar y recomendame algún ajuste sencillo al dashboard que ayude a interpretar mejor los resultados. Además, cuando sea posible, proponé hipótesis de negocio que podrían explicar estos comportamientos, aclarando que se trata de hipótesis y no de conclusiones demostradas por los datos. (Copie y pegue mis tres conclusiones y mi Dashboard Final).
A7: Feedback de ChatGPT | B7: La revisión mediante IA permitió identificar que una mayor facturación no implica necesariamente mayor demanda, rentabilidad o desempeño integral. Los picos de marzo y julio pueden estar asociados al volumen de operaciones, ticket promedio, mix de productos o descuentos. Asimismo, aunque Tecnología lidera la facturación y el Cuarto Trimestre presenta el mayor total trimestral, estos resultados deben interpretarse con cautela antes de atribuirles una causa específica. En particular, las diferencias entre trimestres no permiten afirmar por sí solas la existencia de una tendencia estacional marcada. Se recomienda complementar el análisis con transacciones, unidades vendidas y ticket promedio.
A8: Ajuste realizado en el Dashboard | B8: Se incorporó una nota interpretativa en el dashboard aclarando que el liderazgo del cuarto trimestre debe analizarse juntamente con los KPIs de transacciones y ticket promedio, evitando atribuir el comportamiento a una causa no demostrada por los datos.
